LICENSE
MANIFEST.in
README.md
pynvim.desktop
pynvim.svg
setup.cfg
setup.py
neovim_gui/__init__.py
neovim_gui/cli.py
neovim_gui/gtk_ui.py
neovim_gui/screen.c
neovim_gui/screen.py
neovim_gui/ui_bridge.py
neovim_gui.egg-info/PKG-INFO
neovim_gui.egg-info/SOURCES.txt
neovim_gui.egg-info/dependency_links.txt
neovim_gui.egg-info/entry_points.txt
neovim_gui.egg-info/not-zip-safe
neovim_gui.egg-info/requires.txt
neovim_gui.egg-info/top_level.txt