Metadata-Version: 1.1
Name: neovim-gui
Version: 0.1.3
Summary: Gtk gui for neovim
Home-page: http://github.com/neovim/python-gui
Author: Thiago de Arruda
Author-email: tpadilha84@gmail.com
License: Apache
Download-URL: https://github.com/neovim/python-gui/archive/0.1.3.tar.gz
Platform: UNKNOWN
